monoid_pydev/__init__.py
monoid_pydev/runner.py
monoid_pydev/logger/__init__.py
monoid_pydev/logger/logger.py
monoid_pydev/models/__init__.py
monoid_pydev/models/models.py
monoid_pydev/silos/__init__.py
monoid_pydev/silos/abstract_silo.py
monoid_pydev/silos/data_store.py
monoid_pydev/silos/db_data_store.py
monoid_pydev/utils/__init__.py
monoid_pydev/utils/utils.py
monoid_pydev-0.0.1a2.dist-info/LICENSE
monoid_pydev-0.0.1a2.dist-info/METADATA
monoid_pydev-0.0.1a2.dist-info/WHEEL
monoid_pydev-0.0.1a2.dist-info/top_level.txt
monoid_pydev-0.0.1a2.dist-info/RECORD
