Metadata-Version: 2.1
Name: monoid-pydev
Version: 0.0.1a2
Summary: Tools for building Monoid data silos.
Author-email: "Monoid, Inc." <support@monoid.co>
Project-URL: Homepage, https://www.monoid.co
Project-URL: Bug Tracker, https://github.com/monoid/monoid/issues
Classifier: Programming Language :: Python :: 3
Classifier: License :: OSI Approved :: MIT License
Classifier: Operating System :: OS Independent
Requires-Python: >=3.7
License-File: LICENSE
